shelve_it_cli/__init__.py
shelve_it_cli/archivesspace.py
shelve_it_cli/shelve_it_cli.py
shelve_it_cli-0.1.data/scripts/shelve_it_cli
shelve_it_cli-0.1.dist-info/METADATA
shelve_it_cli-0.1.dist-info/WHEEL
shelve_it_cli-0.1.dist-info/top_level.txt
shelve_it_cli-0.1.dist-info/RECORD
