Metadata-Version: 2.1
Name: shelve-it-cli
Version: 0.1
Summary: Assigning containers to locations in ArchivesSpace
Home-page: https://github.com/lyrasis/shelve_it_cli
Author: Mark Cooper
Author-email: mark.cooper@lyrasis.org
License: MIT
Platform: UNKNOWN
Requires-Dist: ArchivesSnake (==0.7.3)
Requires-Dist: fire (==0.1.3)
